[
    {
      "userId": 1,
      "id": 1,
      "name": "John Doe",
      "email": "john.doe@example.com",
      "title": "Amazing Story!",
      "body": "I was captivated from the very first page. The characters are well developed and the plot is gripping."
    },
    {
      "userId": 2,
      "id": 2,
      "name": "Jane Smith",
      "email": "jane.smith@example.com",
      "title": "Couldn’t Put it Down",
      "body": "An excellent read. The pacing is perfect and the twists kept me on the edge of my seat."
    },
    {
      "userId": 3,
      "id": 3,
      "name": "Alice Johnson",
      "email": "alice.johnson@example.com",
      "title": "Great Characters",
      "body": "The characters in this book are so relatable. I felt like I knew them personally."
    },
    {
      "userId": 4,
      "id": 4,
      "name": "Bob Brown",
      "email": "bob.brown@example.com",
      "title": "Thrilling Adventure",
      "body": "A thrilling adventure from start to finish. Highly recommend it!"
    },
    {
      "userId": 5,
      "id": 5,
      "name": "Charlie Davis",
      "email": "charlie.davis@example.com",
      "title": "Well Written",
      "body": "The writing style is beautiful and immersive. I was completely absorbed in the story."
    },
    {
      "userId": 6,
      "id": 6,
      "name": "Diana Evans",
      "email": "diana.evans@example.com",
      "title": "Fantastic World-Building",
      "body": "The world-building in this book is phenomenal. I felt like I was actually there."
    },
    {
      "userId": 7,
      "id": 7,
      "name": "Ethan Garcia",
      "email": "ethan.garcia@example.com",
      "title": "A Must-Read",
      "body": "One of the best books I’ve read this year. A must-read for any fan of the genre."
    },
    {
      "userId": 8,
      "id": 8,
      "name": "Fiona Harris",
      "email": "fiona.harris@example.com",
      "title": "Emotional Rollercoaster",
      "body": "This book took me on an emotional rollercoaster. I laughed, I cried, and I couldn’t stop reading."
    },
    {
      "userId": 9,
      "id": 9,
      "name": "George King",
      "email": "george.king@example.com",
      "title": "Beautifully Crafted",
      "body": "A beautifully crafted story with rich, detailed descriptions and a compelling plot."
    },
    {
      "userId": 10,
      "id": 10,
      "name": "Hannah Lee",
      "email": "hannah.lee@example.com",
      "title": "Incredible Journey",
      "body": "An incredible journey that kept me hooked from beginning to end. Highly recommend!"
    },
    {
      "userId": 11,
      "id": 11,
      "name": "Ian Martin",
      "email": "ian.martin@example.com",
      "title": "Page Turner",
      "body": "A real page-turner. I couldn’t wait to see what happened next."
    },
    {
      "userId": 12,
      "id": 12,
      "name": "Jasmine Nelson",
      "email": "jasmine.nelson@example.com",
      "title": "Exquisite Prose",
      "body": "The prose is exquisite, and the narrative flow is seamless. A joy to read."
    },
    {
      "userId": 13,
      "id": 13,
      "name": "Kevin Owens",
      "email": "kevin.owens@example.com",
      "title": "Unexpected Twists",
      "body": "Full of unexpected twists and turns. I was constantly surprised."
    },
    {
      "userId": 14,
      "id": 14,
      "name": "Laura Perez",
      "email": "laura.perez@example.com",
      "title": "Heartwarming Story",
      "body": "A heartwarming story that touched my soul. I will definitely be reading this again."
    },
    {
      "userId": 15,
      "id": 15,
      "name": "Mike Quinn",
      "email": "mike.quinn@example.com",
      "title": "Top Notch",
      "body": "Everything about this book is top notch. From the plot to the characters to the setting."
    },
    {
      "userId": 16,
      "id": 16,
      "name": "Nina Roberts",
      "email": "nina.roberts@example.com",
      "title": "Couldn’t Put it Down",
      "body": "An excellent read. The pacing is perfect and the twists kept me on the edge of my seat."
    },
    {
      "userId": 17,
      "id": 17,
      "name": "Oscar Scott",
      "email": "oscar.scott@example.com",
      "title": "Highly Recommended",
      "body": "I highly recommend this book to anyone looking for a great read. You won’t be disappointed."
    },
    {
      "userId": 18,
      "id": 18,
      "name": "Patricia Thomas",
      "email": "patricia.thomas@example.com",
      "title": "Fantastic Read",
      "body": "A fantastic read that I couldn’t put down. The author has done an amazing job."
    },
    {
      "userId": 19,
      "id": 19,
      "name": "Quincy Underwood",
      "email": "quincy.underwood@example.com",
      "title": "Masterpiece",
      "body": "This book is a masterpiece. The story is compelling and the characters are well developed."
    },
    {
      "userId": 20,
      "id": 20,
      "name": "Rachel Vargas",
      "email": "rachel.vargas@example.com",
      "title": "Loved Every Moment",
      "body": "I loved every moment of this book. It’s well-written and highly engaging."
    },
    {
      "userId": 21,
      "id": 21,
      "name": "Sam Walker",
      "email": "sam.walker@example.com",
      "title": "Best Book Ever",
      "body": "This is the best book I’ve ever read. I can’t wait to read more from this author."
    },
    {
      "userId": 22,
      "id": 22,
      "name": "Tina Xu",
      "email": "tina.xu@example.com",
      "title": "A Real Gem",
      "body": "A real gem of a book. The plot is well thought out and the characters are very likable."
    },
    {
      "userId": 23,
      "id": 23,
      "name": "Uma Young",
      "email": "uma.young@example.com",
      "title": "Engaging and Exciting",
      "body": "Engaging and exciting from start to finish. I couldn’t put it down."
    },
    {
      "userId": 24,
      "id": 24,
      "name": "Victor Zane",
      "email": "victor.zane@example.com",
      "title": "Superb",
      "body": "Superb storytelling. I was hooked from the first page to the last."
    },
    {
      "userId": 25,
      "id": 25,
      "name": "Wendy Adams",
      "email": "wendy.adams@example.com",
      "title": "Highly Engaging",
      "body": "Highly engaging and wonderfully written. I enjoyed every bit of it."
    }
  ]
  